badfmt.py
badfmt-1.0.1.dist-info/LICENSE
badfmt-1.0.1.dist-info/METADATA
badfmt-1.0.1.dist-info/WHEEL
badfmt-1.0.1.dist-info/RECORD
