Metadata-Version: 2.1
Name: badfmt
Version: 1.0.1
Summary: A very bad formatter for any programming language with braces and semicolons (eg. c/c++/java/javascript/rust)
Home-page: https://github.com/infibrocco/badfmt
License: MIT
Author: infibrocco
Author-email: infibrocco@github.com
Requires-Python: >=3.8,<4.0
Classifier: License :: OSI Approved :: MIT License
Classifier: Programming Language :: Python :: 3
Classifier: Programming Language :: Python :: 3.8
Classifier: Programming Language :: Python :: 3.9
Classifier: Programming Language :: Python :: 3.10
Classifier: Programming Language :: Python :: 3.11
Classifier: Programming Language :: Python :: 3.12
Requires-Dist: click (>=8.1.7,<9.0.0)
Project-URL: Bug Tracker, https://github.com/infibrocco/badfmt/issues
Project-URL: Repository, https://github.com/infibrocco/badfmt
